nonebot_plugin_litestore-0.1.2.dist-info/METADATA
nonebot_plugin_litestore-0.1.2.dist-info/WHEEL
nonebot_plugin_litestore-0.1.2.dist-info/entry_points.txt
nonebot_plugin_litestore-0.1.2.dist-info/licenses/LICENSE
nonebot_plugin_litestore/__init__.py
nonebot_plugin_litestore/__main__.py
nonebot_plugin_litestore/decorator.py
nonebot_plugin_litestore/model.py
nonebot_plugin_litestore/utils.py
nonebot_plugin_litestore-0.1.2.dist-info/RECORD
