Metadata-Version: 2.1
Name: nonebot_plugin_litestore
Version: 0.1.2
Summary: A Lighter LocalStore For NoneBot2
Author-Email: kanbereina <kano.2525@qq.com>
License: MIT
Requires-Python: >=3.9
Requires-Dist: nonebot2[fastapi]>=2.4.2
Requires-Dist: typing-extensions>=4.12.2
